utils/FileLogger.py
utils/Invaild_Chars.py
utils/__init__.py
utils/arrow_reader.py
utils/csv_chunk_read_util.py
utils/header_detector.py
utils/my_pandas_type_confirming_utils.py
utils/sciencedb_output_info_generator.py
utils/split_file_name_format_checker.py
utils/tab_chunk_read_util.py
utils/thread_util.py
table_file_parer-0.1.3.dist-info/METADATA
table_file_parer-0.1.3.dist-info/WHEEL
table_file_parer-0.1.3.dist-info/top_level.txt
table_file_parer-0.1.3.dist-info/RECORD
