Metadata-Version: 2.4
Name: table_file_parer
Version: 0.1.3
Summary: load table files and parse them into parquet or pyarrow  format
Home-page: https://github.com/yourusername/my_package
Author: qrhan
Author-email: your.email@example.com
Classifier: Programming Language :: Python :: 3
Classifier: License :: OSI Approved :: MIT License
Classifier: Operating System :: OS Independent
Requires-Python: >=3.12
Requires-Dist: chardet<6.0,>=5.0
Requires-Dist: duckdb<2.0,>=1.3
Requires-Dist: h5py<4.0,>=3.10
Requires-Dist: marker<3.0,>=2.1
Requires-Dist: numpy<3.0,>=2.3
Requires-Dist: pandas<3.0,>=2.3
Requires-Dist: psutil<8.0,>=7.0
Requires-Dist: pyarrow<20.0,>=19.0
Requires-Dist: pyreadstat<2.0,>=1.3
Requires-Dist: PyYAML<7.0,>=6.0
Requires-Dist: tdigest<1.0,>=0.5
